dikort/__init__.py
dikort/analyzer.py
dikort/config.py
dikort/filters.py
dikort/main.py
dikort/print.py
dikort/tests/__init__.py
dikort/tests/test_analyzer.py
dikort/tests/test_config.py
dikort/tests/test_filters.py
dikort/tests/test_main.py
dikort/tests/test_print.py
dikort-0.2.1.dist-info/LICENSE
dikort-0.2.1.dist-info/METADATA
dikort-0.2.1.dist-info/WHEEL
dikort-0.2.1.dist-info/entry_points.txt
dikort-0.2.1.dist-info/top_level.txt
dikort-0.2.1.dist-info/RECORD
